youtube_data_extractor/__init__.py
youtube_data_extractor/youtube_data_extractor.py
youtube_data_extractor-0.1.2.dist-info/LICENSE
youtube_data_extractor-0.1.2.dist-info/METADATA
youtube_data_extractor-0.1.2.dist-info/WHEEL
youtube_data_extractor-0.1.2.dist-info/RECORD
