Metadata-Version: 2.1
Name: youtube_data_extractor
Version: 0.1.2
Summary: This is a package that allow you to extract useful information about any youtube video!
License: MIT
Author: YunhongFeng
Requires-Python: >=3.9,<4.0
Classifier: License :: OSI Approved :: MIT License
Classifier: Programming Language :: Python :: 3
Classifier: Programming Language :: Python :: 3.9
Classifier: Programming Language :: Python :: 3.10
Classifier: Programming Language :: Python :: 3.11
